hemekg/__init__.py
hemekg/__main__.py
hemekg-0.0.1.dist-info/LICENSE
hemekg-0.0.1.dist-info/METADATA
hemekg-0.0.1.dist-info/WHEEL
hemekg-0.0.1.dist-info/entry_points.txt
hemekg-0.0.1.dist-info/top_level.txt
hemekg-0.0.1.dist-info/RECORD
