Metadata-Version: 2.1
Name: hemekg
Version: 0.0.1
Summary: Mechanistic knowledge about heme and hemolytic disorders in Biological Expression Language with PyBEL
Home-page: https://github.com/hemekg/hemekg
Author: Farah Humayun and Daniel Domingo-Fernández
Author-email: daniel.domingo.fernandez@scai.fraunhofer.de
Maintainer: Charles Tapley Hoyt
Maintainer-email: cthoyt@gmail.com
License: UNKNOWN
Download-URL: https://github.com/hemekg/hemekg/releases
Project-URL: Bug Tracker, https://github.com/hemekg/hemekg/issues
Project-URL: Source Code, https://github.com/hemekg/hemekg
Platform: UNKNOWN
Requires-Python: >=3.6
Requires-Dist: pybel (>=0.15.0)
